{
    "origin_city_name": "ibrahimabad",
    "destination_city_name": "ishwardi bypass",
    "info": [
        {
            "type": "AC_B",
            "fare": 735.0,
            "vat_percent": 15,
            "vat_amount": 111
        },
        {
            "type": "SNIGDHA",
            "fare": 410.0,
            "vat_percent": 15,
            "vat_amount": 62
        },
        {
            "type": "S_CHAIR",
            "fare": 245.0,
            "vat_percent": 0,
            "vat_amount": 0
        },
        {
            "type": "AC_S",
            "fare": 490.0,
            "vat_percent": 15,
            "vat_amount": 74
        }
    ]
}